easy_dl/__init__.py
easy_dl/config/__init__.py
easy_dl/config/basic_config.py
easy_dl/config/config_parse.py
easy_dl/logger/__init__.py
easy_dl/logger/basic_logger.py
easy_dl/logger/tensorboard_logger.py
easy_dl-0.1.5.dist-info/LICENSE
easy_dl-0.1.5.dist-info/METADATA
easy_dl-0.1.5.dist-info/WHEEL
easy_dl-0.1.5.dist-info/top_level.txt
easy_dl-0.1.5.dist-info/RECORD
