Metadata-Version: 2.1
Name: easy-dl
Version: 0.1.5
Summary: A small package for deep learning that setup config and log metric based on pytorch and tensorboard
Home-page: https://github.com/OnceMonkey/easy-dl
Author: oncemonkey
Classifier: Programming Language :: Python :: 3
Classifier: License :: OSI Approved :: MIT License
Classifier: Operating System :: OS Independent
License-File: LICENSE
